breadcrumb_addressbar/__init__.py
breadcrumb_addressbar/core.py
breadcrumb_addressbar/logger_setup.py
breadcrumb_addressbar/popup.py
breadcrumb_addressbar/themes.py
breadcrumb_addressbar/widgets.py
breadcrumb_addressbar/examples/__init__.py
breadcrumb_addressbar/examples/comprehensive_demo.py
breadcrumb_addressbar-1.0.1.dist-info/METADATA
breadcrumb_addressbar-1.0.1.dist-info/WHEEL
breadcrumb_addressbar-1.0.1.dist-info/licenses/LICENSE
breadcrumb_addressbar-1.0.1.dist-info/RECORD
