Metadata-Version: 2.4
Name: breadcrumb-addressbar
Version: 1.0.1
Summary: A breadcrumb-style address bar for PySide6/PyQt6 file managers with theme support
Author-email: scottlz0310 <scott.lz0310@gmail.com>
License: MIT
License-File: LICENSE
Classifier: Development Status :: 3 - Alpha
Classifier: Intended Audience :: Developers
Classifier: License :: OSI Approved :: MIT License
Classifier: Operating System :: OS Independent
Classifier: Programming Language :: Python :: 3
Classifier: Programming Language :: Python :: 3.12
Classifier: Programming Language :: Python :: 3.13
Classifier: Programming Language :: Python :: 3.14
Requires-Python: >=3.12
Requires-Dist: pyside6>=6.0.0
Requires-Dist: qt-theme-manager>=0.2.0
